juliabridge/__init__.py
juliabridge/bridge.jl
juliabridge/main.py
juliabridge/py.typed
juliabridge-0.2.1.dist-info/METADATA
juliabridge-0.2.1.dist-info/WHEEL
juliabridge-0.2.1.dist-info/licenses/LICENSE
juliabridge-0.2.1.dist-info/RECORD
