Metadata-Version: 2.4
Name: juliabridge
Version: 0.2.1
Summary: A Python package for communicating with Julia.
Project-URL: Homepage, https://github.com/barkure/JuliaBridge
License-File: LICENSE
Classifier: License :: OSI Approved :: MIT License
Classifier: Operating System :: OS Independent
Classifier: Programming Language :: Python :: 3
Requires-Python: >=3.12
Requires-Dist: numpy>=1.23.0
